quilt3/__init__.py
quilt3/admin/__init__.py
quilt3/admin/_graphql_client/__init__.py
quilt3/admin/_graphql_client/base_client.py
quilt3/admin/_graphql_client/base_model.py
quilt3/admin/_graphql_client/bucket_add.py
quilt3/admin/_graphql_client/bucket_get.py
quilt3/admin/_graphql_client/bucket_remove.py
quilt3/admin/_graphql_client/bucket_tabulator_table_rename.py
quilt3/admin/_graphql_client/bucket_tabulator_table_set.py
quilt3/admin/_graphql_client/bucket_tabulator_tables_list.py
quilt3/admin/_graphql_client/bucket_update.py
quilt3/admin/_graphql_client/buckets_list.py
quilt3/admin/_graphql_client/client.py
quilt3/admin/_graphql_client/enums.py
quilt3/admin/_graphql_client/exceptions.py
quilt3/admin/_graphql_client/fragments.py
quilt3/admin/_graphql_client/input_types.py
quilt3/admin/_graphql_client/roles_list.py
quilt3/admin/_graphql_client/sso_config_get.py
quilt3/admin/_graphql_client/sso_config_set.py
quilt3/admin/_graphql_client/tabulator_get_open_query.py
quilt3/admin/_graphql_client/tabulator_set_open_query.py
quilt3/admin/_graphql_client/users_add_roles.py
quilt3/admin/_graphql_client/users_create.py
quilt3/admin/_graphql_client/users_delete.py
quilt3/admin/_graphql_client/users_get.py
quilt3/admin/_graphql_client/users_list.py
quilt3/admin/_graphql_client/users_remove_roles.py
quilt3/admin/_graphql_client/users_reset_password.py
quilt3/admin/_graphql_client/users_set_active.py
quilt3/admin/_graphql_client/users_set_admin.py
quilt3/admin/_graphql_client/users_set_email.py
quilt3/admin/_graphql_client/users_set_role.py
quilt3/admin/buckets.py
quilt3/admin/exceptions.py
quilt3/admin/roles.py
quilt3/admin/sso_config.py
quilt3/admin/tabulator.py
quilt3/admin/types.py
quilt3/admin/users.py
quilt3/admin/util.py
quilt3/api.py
quilt3/backends/__init__.py
quilt3/backends/base.py
quilt3/backends/local.py
quilt3/backends/s3.py
quilt3/bucket.py
quilt3/data_transfer.py
quilt3/exceptions.py
quilt3/formats.py
quilt3/hooks.py
quilt3/imports.py
quilt3/main.py
quilt3-7.1.0.dist-info/licenses/LICENSE
quilt3-7.1.0.dist-info/WHEEL
quilt3-7.1.0.dist-info/entry_points.txt
quilt3-7.1.0.dist-info/METADATA
quilt3-7.1.0.dist-info/RECORD
