Metadata-Version: 2.4
Name: quilt3
Version: 7.1.0
Summary: Quilt: where data comes together
Author: quiltdata
Author-email: quiltdata <contact@quiltdata.io>
License-Expression: Apache-2.0
License-File: LICENSE
Classifier: Development Status :: 5 - Production/Stable
Classifier: Intended Audience :: Developers
Classifier: Operating System :: OS Independent
Classifier: Programming Language :: Python :: 3.9
Classifier: Programming Language :: Python :: 3.10
Classifier: Programming Language :: Python :: 3.11
Classifier: Programming Language :: Python :: 3.12
Classifier: Programming Language :: Python :: 3.13
Classifier: Programming Language :: Python :: 3.14
Requires-Dist: platformdirs>=2
Requires-Dist: boto3>=1.21.7
Requires-Dist: jsonlines==1.2.0
Requires-Dist: pyyaml>=5.1
Requires-Dist: requests>=2.12.4
Requires-Dist: tenacity>=5.1.1,!=8.4.0
Requires-Dist: tqdm>=4.32
Requires-Dist: requests-futures==1.0.0
Requires-Dist: jsonschema>=3,<5
Requires-Dist: pydantic>=2.0.0,<3.0.0
Requires-Dist: anndata>=0.8.0 ; extra == 'anndata'
Requires-Dist: quilt3-local>=2,<3 ; extra == 'catalog'
Requires-Dist: uvicorn>=0.15,<0.18 ; extra == 'catalog'
Requires-Dist: aiobotocore[boto3]>=2 ; extra == 'catalog'
Requires-Dist: numpy>=1.14.0 ; extra == 'pyarrow'
Requires-Dist: pandas>=0.19.2 ; extra == 'pyarrow'
Requires-Dist: pyarrow>=0.14.1 ; extra == 'pyarrow'
Requires-Python: >=3.9
Project-URL: Changelog, https://docs.quilt.bio/quilt-python-sdk/more/changelog
Project-URL: Documentation, https://docs.quilt.bio/#quilt-python-sdk
Project-URL: Homepage, https://quilt.bio/
Project-URL: Issues, https://github.com/quiltdata/quilt/issues
Project-URL: Repository, https://github.com/quiltdata/quilt
Provides-Extra: anndata
Provides-Extra: catalog
Provides-Extra: pyarrow
